tests/__init__.py
tests/test_text.py
thaibraille/__init__.py
thaibraille/text/__init__.py
thaibraille/text/core.py
thaibraille-0.1.dev2.dist-info/LICENSE
thaibraille-0.1.dev2.dist-info/METADATA
thaibraille-0.1.dev2.dist-info/WHEEL
thaibraille-0.1.dev2.dist-info/top_level.txt
thaibraille-0.1.dev2.dist-info/RECORD
