Metadata-Version: 2.1
Name: thaibraille
Version: 0.1.dev2
Summary: Thai Braille for Natural Language Processing.
Home-page: https://github.com/pythainlp/thaibraille
Author: Wannaphong Phatthiyaphaibun
Author-email: wannaphong@yahoo.com
License: Apache Software License 2.0
Project-URL: Source, https://github.com/pythainlp/thaibraille
Project-URL: Bug Reports, https://github.com/pythainlp/thaibraille/issues
Keywords: thai,NLP,natural language processing,text analytics,text processing,localization,computational linguistics,thai language
Classifier: Development Status :: 3 - Alpha
Classifier: Programming Language :: Python :: 3
Classifier: Intended Audience :: Developers
Classifier: License :: OSI Approved :: Apache Software License
Classifier: Topic :: Scientific/Engineering :: Artificial Intelligence
Classifier: Topic :: Text Processing
Classifier: Topic :: Text Processing :: General
Classifier: Topic :: Text Processing :: Linguistic
Requires-Python: >=3.6
License-File: LICENSE
Requires-Dist: pythainlp (>=3.1.0)
